Metadata-Version: 1.0
Name: gnbo-distribution
Version: 0.2
Summary: Gaussian Distribution and Binomial Distribution
Home-page: UNKNOWN
Author: UNKNOWN
Author-email: UNKNOWN
License: UNKNOWN
Platform: UNKNOWN
